{"otherData": {},"traceEvents":[{"cat":"function","dur":30922,"name":"glfw init","ph":"X","pid":0,"tid":1342374587,"ts":34856965752},{"cat":"function","dur":259092,"name":"glfwCreateWindow","ph":"X","pid":0,"tid":1342374587,"ts":34856996834},{"cat":"function","dur":2223,"name":"void __cdecl Mayhem::OpenGLContext::Init(void)","ph":"X","pid":0,"tid":1342374587,"ts":34857256009},{"cat":"function","dur":27,"name":"void __cdecl Mayhem::WindowsWindow::SetVSync(bool)","ph":"X","pid":0,"tid":1342374587,"ts":34857258353},{"cat":"function","dur":293890,"name":"void __cdecl Mayhem::WindowsWindow::Init(const struct Mayhem::WindowProps &)","ph":"X","pid":0,"tid":1342374587,"ts":34856964608},{"cat":"function","dur":293915,"name":"__cdecl Mayhem::WindowsWindow::WindowsWindow(const struct Mayhem::WindowProps &)","ph":"X","pid":0,"tid":1342374587,"ts":34856964606},{"cat":"function","dur":4,"name":"void __cdecl Mayhem::OpenGLRendererAPI::Init(void)","ph":"X","pid":0,"tid":1342374587,"ts":34857258555},{"cat":"function","dur":30,"name":"__cdecl Mayhem::OpenGLVertexArray::OpenGLVertexArray(void)","ph":"X","pid":0,"tid":1342374587,"ts":34857258587},{"cat":"function","dur":23,"name":"__cdecl Mayhem::OpenGLVertexBuffer::OpenGLVertexBuffer(float *,unsigned int)","ph":"X","pid":0,"tid":1342374587,"ts":34857258662},{"cat":"function","dur":1,"name":"void __cdecl Mayhem::OpenGLVertexBuffer::Bind(void) const","ph":"X","pid":0,"tid":1342374587,"ts":34857258933},{"cat":"function","dur":403,"name":"void __cdecl Mayhem::OpenGLVertexArray::AddVertexBuffer(const class std::shared_ptr<class Mayhem::VertexBuffer> &)","ph":"X","pid":0,"tid":1342374587,"ts":34857258713},{"cat":"function","dur":40,"name":"__cdecl Mayhem::OpenGLIndexBuffer::OpenGLIndexBuffer(unsigned int *,unsigned int)","ph":"X","pid":0,"tid":1342374587,"ts":34857259136},{"cat":"function","dur":0,"name":"void __cdecl Mayhem::OpenGLIndexBuffer::Bind(void) const","ph":"X","pid":0,"tid":1342374587,"ts":34857259196},{"cat":"function","dur":18,"name":"void __cdecl Mayhem::OpenGLVertexArray::SetIndexBuffer(const class std::shared_ptr<class Mayhem::IndexBuffer> &)","ph":"X","pid":0,"tid":1342374587,"ts":34857259195},{"cat":"function","dur":28,"name":"__cdecl Mayhem::OpenGLTexture2D::OpenGLTexture2D(unsigned int,unsigned int)","ph":"X","pid":0,"tid":1342374587,"ts":34857259236},{"cat":"function","dur":4,"name":"void __cdecl Mayhem::OpenGLTexture2D::SetData(void *,unsigned int)","ph":"X","pid":0,"tid":1342374587,"ts":34857259287},{"cat":"function","dur":244,"name":"class std::basic_string<char,struct std::char_traits<char>,class std::allocator<char> > __cdecl Mayhem::OpenGLShader::ReadFile(const class std::basic_string<char,struct std::char_traits<char>,class std::allocator<char> > &)","ph":"X","pid":0,"tid":1342374587,"ts":34857259317},{"cat":"function","dur":30,"name":"class std::unordered_map<unsigned int,class std::basic_string<char,struct std::char_traits<char>,class std::allocator<char> >,struct std::hash<unsigned int>,struct std::equal_to<unsigned int>,class std::allocator<struct std::pair<unsigned int const ,class std::basic_string<char,struct std::char_traits<char>,class std::allocator<char> > > > > __cdecl Mayhem::OpenGLShader::PreProcess(const class std::basic_string<char,struct std::char_traits<char>,class std::allocator<char> > &)","ph":"X","pid":0,"tid":1342374587,"ts":34857259587},{"cat":"function","dur":326,"name":"void __cdecl Mayhem::OpenGLShader::Compile(const class std::unordered_map<unsigned int,class std::basic_string<char,struct std::char_traits<char>,class std::allocator<char> >,struct std::hash<unsigned int>,struct std::equal_to<unsigned int>,class std::allocator<struct std::pair<unsigned int const ,class std::basic_string<char,struct std::char_traits<char>,class std::allocator<char> > > > > &)","ph":"X","pid":0,"tid":1342374587,"ts":34857259633},{"cat":"function","dur":668,"name":"__cdecl Mayhem::OpenGLShader::OpenGLShader(const class std::basic_string<char,struct std::char_traits<char>,class std::allocator<char> > &)","ph":"X","pid":0,"tid":1342374587,"ts":34857259315},{"cat":"function","dur":1,"name":"void __cdecl Mayhem::OpenGLShader::Bind(void) const","ph":"X","pid":0,"tid":1342374587,"ts":34857260003},{"cat":"function","dur":31,"name":"void __cdecl Mayhem::OpenGLShader::SetInt(const class std::basic_string<char,struct std::char_traits<char>,class std::allocator<char> > &,int)","ph":"X","pid":0,"tid":1342374587,"ts":34857260047},{"cat":"function","dur":1524,"name":"void __cdecl Mayhem::Renderer2D::Init(void)","ph":"X","pid":0,"tid":1342374587,"ts":34857258576},{"cat":"function","dur":1560,"name":"void __cdecl Mayhem::Renderer::Init(void)","ph":"X","pid":0,"tid":1342374587,"ts":34857258555},{"cat":"function","dur":559,"name":"void __cdecl Mayhem::ImGuiLayer::OnAttach(void)","ph":"X","pid":0,"tid":1342374587,"ts":34857260137},{"cat":"function","dur":597,"name":"void __cdecl Mayhem::Application::PushOverlay(class Mayhem::Layer *)","ph":"X","pid":0,"tid":1342374587,"ts":34857260133},{"cat":"function","dur":296157,"name":"__cdecl Mayhem::Application::Application(void)","ph":"X","pid":0,"tid":1342374587,"ts":34856964589},{"cat":"function","dur":2,"name":"__cdecl Mayhem::OrthographicCamera::OrthographicCamera(float,float,float,float)","ph":"X","pid":0,"tid":1342374587,"ts":34857260769},{"cat":"function","dur":284,"name":"stbi_load - OpenGLTexture2D::OpenGLTexture2D(const std::string&)","ph":"X","pid":0,"tid":1342374587,"ts":34857260798},{"cat":"function","dur":334,"name":"__cdecl Mayhem::OpenGLTexture2D::OpenGLTexture2D(const class std::basic_string<char,struct std::char_traits<char>,class std::allocator<char> > &)","ph":"X","pid":0,"tid":1342374587,"ts":34857260798},{"cat":"function","dur":357,"name":"void __cdecl Sandbox2D::OnAttach(void)","ph":"X","pid":0,"tid":1342374587,"ts":34857260796},{"cat":"function","dur":379,"name":"void __cdecl Mayhem::Application::PushLayer(class Mayhem::Layer *)","ph":"X","pid":0,"tid":1342374587,"ts":34857260793}]}