{"otherData": {},"traceEvents":[{"cat":"function","dur":1,"name":"__cdecl Mayhem::OpenGLTexture2D::~OpenGLTexture2D(void)","ph":"X","pid":0,"tid":2457344047,"ts":51635436164},{"cat":"function","dur":0,"name":"__cdecl Mayhem::OpenGLShader::~OpenGLShader(void)","ph":"X","pid":0,"tid":2457344047,"ts":51635436195},{"cat":"function","dur":0,"name":"__cdecl Mayhem::OpenGLVertexArray::~OpenGLVertexArray(void)","ph":"X","pid":0,"tid":2457344047,"ts":51635436212},{"cat":"function","dur":1,"name":"__cdecl Mayhem::OpenGLIndexBuffer::~OpenGLIndexBuffer(void)","ph":"X","pid":0,"tid":2457344047,"ts":51635436227},{"cat":"function","dur":0,"name":"__cdecl Mayhem::OpenGLVertexBuffer::~OpenGLVertexBuffer(void)","ph":"X","pid":0,"tid":2457344047,"ts":51635436243},{"cat":"function","dur":98,"name":"void __cdecl Mayhem::Renderer2D::Shutdown(void)","ph":"X","pid":0,"tid":2457344047,"ts":51635436163},{"cat":"function","dur":113,"name":"__cdecl Mayhem::Application::~Application(void)","ph":"X","pid":0,"tid":2457344047,"ts":51635436162},{"cat":"function","dur":0,"name":"void __cdecl Sandbox2D::OnDetach(void)","ph":"X","pid":0,"tid":2457344047,"ts":51635436290},{"cat":"function","dur":1,"name":"__cdecl Mayhem::OpenGLTexture2D::~OpenGLTexture2D(void)","ph":"X","pid":0,"tid":2457344047,"ts":51635436303},{"cat":"function","dur":1027,"name":"void __cdecl Mayhem::ImGuiLayer::OnDetach(void)","ph":"X","pid":0,"tid":2457344047,"ts":51635436319},{"cat":"function","dur":8983,"name":"void __cdecl Mayhem::WindowsWindow::Shutdown(void)","ph":"X","pid":0,"tid":2457344047,"ts":51635437387},{"cat":"function","dur":9059,"name":"__cdecl Mayhem::WindowsWindow::~WindowsWindow(void)","ph":"X","pid":0,"tid":2457344047,"ts":51635437387}]}